plone.app.z3cform-4.7.9-py3.13-nspkg.pth
plone/app/z3cform/__init__.py
plone/app/z3cform/configure.zcml
plone/app/z3cform/converters.py
plone/app/z3cform/converters.zcml
plone/app/z3cform/csrf.py
plone/app/z3cform/factories.py
plone/app/z3cform/inline_validation.py
plone/app/z3cform/inline_validation.rst
plone/app/z3cform/interfaces.py
plone/app/z3cform/layout.py
plone/app/z3cform/overrides.zcml
plone/app/z3cform/profiles.zcml
plone/app/z3cform/utils.py
plone/app/z3cform/views.py
plone/app/z3cform/widget.py
plone/app/z3cform/widgets.zcml
plone/app/z3cform/profiles/default/browserlayer.xml
plone/app/z3cform/profiles/default/metadata.xml
plone/app/z3cform/templates/ajaxselect_display.pt
plone/app/z3cform/templates/checkbox_input.pt
plone/app/z3cform/templates/contentbrowser_display.pt
plone/app/z3cform/templates/contentprovider-widget.pt
plone/app/z3cform/templates/email_input.pt
plone/app/z3cform/templates/error.pt
plone/app/z3cform/templates/file_input.pt
plone/app/z3cform/templates/form.pt
plone/app/z3cform/templates/image_input.pt
plone/app/z3cform/templates/layout.pt
plone/app/z3cform/templates/link_input.pt
plone/app/z3cform/templates/macros.pt
plone/app/z3cform/templates/multi_input.pt
plone/app/z3cform/templates/object_input.pt
plone/app/z3cform/templates/orderedselect_input.pt
plone/app/z3cform/templates/password_input.pt
plone/app/z3cform/templates/radio_input.pt
plone/app/z3cform/templates/radio_input_single.pt
plone/app/z3cform/templates/relateditems_display.pt
plone/app/z3cform/templates/richtext_input.pt
plone/app/z3cform/templates/select_input.pt
plone/app/z3cform/templates/singlecheckbox.pt
plone/app/z3cform/templates/singlecheckboxbool_display.pt
plone/app/z3cform/templates/singlecheckboxbool_hidden.pt
plone/app/z3cform/templates/singlecheckboxbool_input.pt
plone/app/z3cform/templates/submit_input.pt
plone/app/z3cform/templates/text_input.pt
plone/app/z3cform/templates/textarea_input.pt
plone/app/z3cform/templates/textlines_input.pt
plone_app_z3cform-4.7.9.dist-info/METADATA
plone_app_z3cform-4.7.9.dist-info/WHEEL
plone_app_z3cform-4.7.9.dist-info/namespace_packages.txt
plone_app_z3cform-4.7.9.dist-info/top_level.txt
plone_app_z3cform-4.7.9.dist-info/RECORD
