Metadata-Version: 2.4
Name: plone.app.z3cform
Version: 4.7.9
Summary: A collection of widgets, templates and other components for use with z3c.form and Plone
Home-page: https://pypi.org/project/plone.app.z3cform
Author: Plone Foundation
Author-email: plone-developers@lists.sourceforge.net
License: GPL
Keywords: zope plone form widget template
Classifier: Development Status :: 5 - Production/Stable
Classifier: Environment :: Web Environment
Classifier: Framework :: Plone
Classifier: Framework :: Plone :: 6.0
Classifier: Framework :: Plone :: Core
Classifier: Framework :: Zope :: 5
Classifier: License :: OSI Approved :: GNU General Public License v2 (GPLv2)
Classifier: Operating System :: OS Independent
Classifier: Programming Language :: Python
Classifier: Programming Language :: Python :: 3.8
Classifier: Programming Language :: Python :: 3.9
Classifier: Programming Language :: Python :: 3.10
Classifier: Programming Language :: Python :: 3.11
Requires-Python: >=3.8
Requires-Dist: plone.app.textfield>=1.3.6
Requires-Dist: plone.base
Requires-Dist: plone.app.contentlisting
Requires-Dist: plone.formwidget.namedfile>=3.1.0
Requires-Dist: plone.i18n
Requires-Dist: plone.protect
Requires-Dist: plone.registry
Requires-Dist: plone.schema
Requires-Dist: plone.uuid
Requires-Dist: plone.z3cform
Requires-Dist: Products.GenericSetup
Requires-Dist: pytz
Requires-Dist: setuptools
Requires-Dist: z3c.form>=5.1
Requires-Dist: z3c.relationfield
Requires-Dist: zope.deprecation
Requires-Dist: zope.globalrequest
Requires-Dist: Zope
Provides-Extra: test
Requires-Dist: plone.app.contenttypes[test]; extra == "test"
Requires-Dist: plone.app.testing; extra == "test"
Requires-Dist: plone.autoform; extra == "test"
Requires-Dist: plone.browserlayer; extra == "test"
Requires-Dist: plone.dexterity; extra == "test"
Requires-Dist: plone.supermodel; extra == "test"
Requires-Dist: plone.testing; extra == "test"
Requires-Dist: zope.annotation; extra == "test"
Requires-Dist: zope.intid; extra == "test"
Requires-Dist: zope.publisher; extra == "test"
Provides-Extra: tests
Requires-Dist: plone.app.contenttypes[test]; extra == "tests"
Requires-Dist: plone.app.testing; extra == "tests"
Requires-Dist: plone.autoform; extra == "tests"
Requires-Dist: plone.browserlayer; extra == "tests"
Requires-Dist: plone.dexterity; extra == "tests"
Requires-Dist: plone.supermodel; extra == "tests"
Requires-Dist: plone.testing; extra == "tests"
Requires-Dist: zope.annotation; extra == "tests"
Requires-Dist: zope.intid; extra == "tests"
Requires-Dist: zope.publisher; extra == "tests"
Dynamic: author
Dynamic: author-email
Dynamic: classifier
Dynamic: description
Dynamic: description-content-type
Dynamic: home-page
Dynamic: keywords
Dynamic: license
Dynamic: provides-extra
Dynamic: requires-dist
Dynamic: requires-python
Dynamic: summary
